<?xml version="1.0" encoding="UTF-8" standalone="no"?>
<taskData>
    <task>
        <id>2</id>
        <date>2026-04-28</date>
        <time>09:00</time>
        <content>pppppp</content>
    </task>
    <task>
        <id>3</id>
        <date>2026-04-20</date>
        <time>09:00</time>
        <content>opppp</content>
    </task>
    <task>
        <id>4</id>
        <date>2026-04-20</date>
        <time>08:00</time>
        <content>okkkk</content>
    </task>
    <task>
        <id>5</id>
        <date>2026-04-22</date>
        <time>08:00</time>
        <content>ottttt</content>
    </task>
    <task>
        <id>6</id>
        <date>2026-04-20</date>
        <time>22:54</time>
        <content>checktime</content>
    </task>
</taskData>
